hhgrdiff/__init__.py
hhgrdiff/__main__.py
hhgrdiff/hhgrdiff.py
hhgrdiff/version.py
hardhat_gas_report_diff-0.1.0.dist-info/LICENSE
hardhat_gas_report_diff-0.1.0.dist-info/METADATA
hardhat_gas_report_diff-0.1.0.dist-info/WHEEL
hardhat_gas_report_diff-0.1.0.dist-info/top_level.txt
hardhat_gas_report_diff-0.1.0.dist-info/RECORD
