Metadata-Version: 2.1
Name: hardhat-gas-report-diff
Version: 0.1.0
Summary: Hardhat Gas Report Diff
Home-page: https://github.com/guidanoli/hardhat-gas-report-diff
Author: Guilherme Dantas
Author-email: guidanoli@hotmail.com
License: GNU General Public License v3.0
Project-URL: Bug Tracker, https://github.com/guidanoli/hardhat-gas-report-diff/issues
Classifier: Development Status :: 5 - Production/Stable
Classifier: Environment :: Console
Classifier: Intended Audience :: Developers
Classifier: Intended Audience :: Science/Research
Classifier: License :: OSI Approved :: GNU General Public License v3 (GPLv3)
Classifier: Programming Language :: Python :: 3.8
Classifier: Topic :: Text Processing
Classifier: Topic :: Utilities
Requires-Python: >=3.8
License-File: LICENSE
